<?xml version="1.0" encoding="UTF-8"?>
<!-- Created with TexturePacker http://www.codeandweb.com/texturepacker-->
<!-- $TexturePacker:SmartUpdate:8b07eeee560a677e8e7729bb9423e026:33786ae80014b52de82e991248e8a855:407de1f245c0fc25239dff1ad1c4bb30$ -->
<!--Format:
n  => name of the sprite
x  => sprite x pos in texture
y  => sprite y pos in texture
w  => sprite width (may be trimmed)
h  => sprite height (may be trimmed)
oX => sprite's x-corner offset (only available if trimmed)
oY => sprite's y-corner offset (only available if trimmed)
oW => sprite's original width (only available if trimmed)
oH => sprite's original height (only available if trimmed)
r => 'y' only set if sprite is rotated
-->
<TextureAtlas imagePath="pre-laser-glow.png" width="512" height="1024">
    <sprite n="barbie-animation-laser-glow-01.png" x="436" y="512" w="44" h="233" oX="13" oY="20" oW="70" oH="273"/>
    <sprite n="barbie-animation-laser-glow-02.png" x="386" y="261" w="48" h="251" oX="11" oY="11" oW="70" oH="273"/>
    <sprite n="barbie-animation-laser-glow-03.png" x="46" y="747" w="42" h="245" oX="15" oY="15" oW="70" oH="273"/>
    <sprite n="barbie-animation-laser-glow-04.png" x="132" y="747" w="38" h="241" oX="16" oY="16" oW="70" oH="273"/>
    <sprite n="barbie-animation-laser-glow-05.png" x="268" y="265" w="46" h="249" oX="12" oY="12" oW="70" oH="273"/>
    <sprite n="barbie-animation-laser-glow-06.png" x="386" y="2" w="54" h="257" oX="8" oY="8" oW="70" oH="273"/>
    <sprite n="barbie-animation-laser-glow-07.png" x="204" y="2" w="62" h="265" oX="4" oY="4" oW="70" oH="273"/>
    <sprite n="barbie-animation-laser-glow-08.png" x="2" y="2" w="70" h="273"/>
    <sprite n="barbie-animation-laser-glow-09.png" x="140" y="2" w="62" h="265" oX="4" oY="4" oW="70" oH="273"/>
    <sprite n="barbie-animation-laser-glow-10.png" x="328" y="2" w="56" h="259" oX="7" oY="7" oW="70" oH="273"/>
    <sprite n="barbie-animation-laser-glow-11.png" x="442" y="259" w="48" h="251" oX="11" oY="11" oW="70" oH="273"/>
    <sprite n="barbie-animation-laser-glow-12.png" x="2" y="747" w="42" h="245" oX="14" oY="14" oW="70" oH="273"/>
    <sprite n="barbie-animation-laser-glow-13.png" x="172" y="747" w="34" h="237" oX="18" oY="18" oW="70" oH="273"/>
    <sprite n="barbie-animation-laser-glow-14.png" x="90" y="747" w="40" h="243" oX="15" oY="15" oW="70" oH="273"/>
    <sprite n="barbie-animation-laser-glow-15.png" x="328" y="263" w="46" h="249" oX="12" oY="12" oW="70" oH="273"/>
    <sprite n="barbie-animation-laser-glow-16.png" x="442" y="2" w="52" h="255" oX="9" oY="9" oW="70" oH="273"/>
    <sprite n="barbie-animation-laser-glow-17.png" x="268" y="2" w="58" h="261" oX="6" oY="6" oW="70" oH="273"/>
    <sprite n="barbie-animation-laser-glow-18.png" x="74" y="2" w="64" h="267" oX="3" oY="3" oW="70" oH="273"/>
    <sprite n="barbie-animation-laser-glow-19.png" x="2" y="2" w="70" h="273"/>
    <sprite n="barbie-animation-laser-glow-20.png" x="74" y="2" w="64" h="267" oX="3" oY="3" oW="70" oH="273"/>
    <sprite n="barbie-animation-laser-glow-21.png" x="268" y="2" w="58" h="261" oX="6" oY="6" oW="70" oH="273"/>
    <sprite n="barbie-animation-laser-glow-22.png" x="442" y="2" w="52" h="255" oX="9" oY="9" oW="70" oH="273"/>
    <sprite n="barbie-animation-laser-glow-23.png" x="328" y="263" w="46" h="249" oX="12" oY="12" oW="70" oH="273"/>
    <sprite n="barbie-animation-laser-glow-24.png" x="90" y="747" w="40" h="243" oX="15" oY="15" oW="70" oH="273"/>
    <sprite n="barbie-animation-laser-glow-25.png" x="172" y="747" w="34" h="237" oX="18" oY="18" oW="70" oH="273"/>
    <sprite n="barbie-animation-laser-glow-26.png" x="482" y="512" w="28" h="231" oX="21" oY="21" oW="70" oH="273"/>
    <sprite n="barbie-animation-laser-glow-27.png" x="482" y="745" w="20" h="223" oX="25" oY="25" oW="70" oH="273"/>
    <sprite n="barbie-animation-laser-glow-28.png" x="496" y="2" w="14" h="217" oX="28" oY="28" oW="70" oH="273"/>
</TextureAtlas>
