<?xml version="1.0" encoding="UTF-8"?>
<map version="1.0" orientation="orthogonal" renderorder="right-down" width="25" height="20" tilewidth="256" tileheight="256" nextobjectid="145">
 <tileset firstgid="1" name="Objects" tilewidth="219" tileheight="229" tilecount="4" columns="0">
  <tile id="0">
   <image width="64" height="128" source="../images/temp/player.png"/>
  </tile>
  <tile id="1">
   <image width="128" height="128" source="../images/temp/dcshg-game-crates-01.png"/>
  </tile>
  <tile id="2">
   <image width="64" height="64" source="../images/temp/collectible.png"/>
  </tile>
  <tile id="3">
   <image width="219" height="229" source="../images/gameplay/cart_game/barbie-dt-rc-bg-obstacles.png"/>
  </tile>
 </tileset>
 <tileset firstgid="5" name="barbie-dt-1024-tile_1" tilewidth="256" tileheight="256" tilecount="16" columns="4">
  <image source="images/barbie-dt-1024-tile_1.png" width="1024" height="1024"/>
 </tileset>
 <tileset firstgid="21" name="barbie-dt-1024-tile_4" tilewidth="256" tileheight="256" tilecount="16" columns="4">
  <image source="images/barbie-dt-1024-tile_4.png" width="1024" height="1024"/>
 </tileset>
 <tileset firstgid="37" name="Objects" tilewidth="256" tileheight="256" tilecount="2" columns="0">
  <tile id="0">
   <image width="64" height="64" source="../images/temp/collectible.png"/>
  </tile>
  <tile id="1">
   <image width="114" height="113" source="../images/gameplay/cart_game/dcshg-collect-coin.png"/>
  </tile>
 </tileset>
 <tileset firstgid="39" name="barbie-dt2-sparkmtn-deco-mid-6" tilewidth="247" tileheight="375" tilecount="1" columns="1">
  <image source="images/barbie-dt2-sparkmtn-deco-mid-6.png" width="247" height="375"/>
 </tileset>
 <tileset firstgid="40" name="barbie-dt2-sparkmtn-deco-mid-7" tilewidth="151" tileheight="201" tilecount="1" columns="1">
  <image source="images/barbie-dt2-sparkmtn-deco-mid-7.png" width="151" height="201"/>
 </tileset>
 <tileset firstgid="41" name="barbie-dt2-sparkmtn-deco-mid-4" tilewidth="177" tileheight="359" tilecount="1" columns="1">
  <image source="images/barbie-dt2-sparkmtn-deco-mid-4.png" width="177" height="359"/>
 </tileset>
 <tileset firstgid="42" name="barbie-dt2-sparkmtn-deco-mid-2" tilewidth="229" tileheight="611" tilecount="1" columns="1">
  <image source="images/barbie-dt2-sparkmtn-deco-mid-2.png" width="229" height="611"/>
 </tileset>
 <tileset firstgid="43" name="barbie-dt2-sparkmtn-deco-mid-3" tilewidth="201" tileheight="587" tilecount="1" columns="1">
  <image source="images/barbie-dt2-sparkmtn-deco-mid-3.png" width="201" height="587"/>
 </tileset>
 <objectgroup name="BG2">
  <object id="108" type="Decoration" gid="41" x="3784" y="1863" width="177" height="359"/>
 </objectgroup>
 <objectgroup name="BG1">
  <object id="104" type="Decoration" gid="39" x="925" y="2651" width="247" height="375"/>
  <object id="105" type="Decoration" gid="39" x="4781" y="2299" width="247" height="375"/>
  <object id="106" type="Decoration" gid="40" x="3685" y="1836" width="151" height="201"/>
  <object id="107" type="Decoration" gid="41" x="1560" y="2691" width="177" height="359"/>
 </objectgroup>
 <layer name="Tiles" width="25" height="20">
  <data encoding="csv">
0,0,0,0,0,0,0,0,0,0,0,0,0,0,0,0,0,0,0,0,0,0,0,0,0,
0,0,0,0,0,0,0,0,0,0,0,0,0,0,0,0,0,0,0,0,0,0,0,0,0,
0,0,0,0,0,0,0,0,0,0,0,0,0,0,0,0,0,0,0,0,0,0,0,0,0,
0,0,0,0,0,0,0,0,0,0,0,0,0,0,0,0,0,0,0,0,0,0,0,0,0,
0,0,0,0,0,0,0,0,0,0,0,0,0,0,0,0,0,0,0,0,0,0,0,0,0,
0,0,0,0,0,0,0,0,0,0,0,0,0,0,0,0,0,0,0,0,0,0,0,0,0,
0,0,0,0,0,0,0,0,0,0,0,0,0,0,0,0,0,0,0,0,0,0,0,0,0,
0,0,0,0,0,0,0,0,0,0,0,0,0,2147483681,5,6,7,8,0,0,0,0,0,0,0,
0,0,0,0,0,0,0,0,0,0,0,0,0,2147483682,9,10,11,12,13,14,0,0,0,0,0,
0,0,0,0,0,0,9,10,0,0,0,0,0,2147483683,0,0,0,0,17,18,0,0,0,0,0,
0,0,0,5,6,2147483654,2147483653,33,0,0,0,0,0,2147483684,0,0,0,0,0,0,0,0,0,0,0,
0,0,0,0,0,0,0,34,0,0,0,0,0,0,0,0,0,0,0,0,0,0,0,0,0,
0,0,0,0,0,0,0,35,0,0,0,0,0,0,0,0,0,0,0,0,0,0,0,0,0,
0,0,0,0,0,0,0,36,0,0,0,0,0,0,0,0,0,0,0,0,0,0,0,0,0,
0,0,0,0,0,0,0,0,0,0,0,0,0,0,0,0,0,0,0,0,0,0,0,0,0,
0,0,0,0,0,0,0,0,0,0,0,0,0,0,0,0,0,0,0,0,0,0,0,0,0,
0,0,0,0,0,0,0,0,0,0,0,0,0,0,0,0,0,0,0,0,0,0,0,0,0,
0,0,0,0,0,0,0,0,0,0,0,0,0,0,0,0,0,0,0,0,0,0,0,0,0,
0,0,0,0,0,0,0,0,0,0,0,0,0,0,0,0,0,0,0,0,0,0,0,0,0,
0,0,0,0,0,0,0,0,0,0,0,0,0,0,0,0,0,0,0,0,0,0,0,0,0
</data>
 </layer>
 <layer name="Foreground" width="25" height="20">
  <data encoding="csv">
0,0,0,0,0,0,0,0,0,0,0,0,0,0,0,0,0,0,0,0,0,0,0,0,0,
0,0,0,0,0,0,0,0,0,0,0,0,0,0,0,0,0,0,0,0,0,0,0,0,0,
0,0,0,0,0,0,0,0,0,0,0,0,0,0,0,0,0,0,0,0,0,0,0,0,0,
0,0,0,0,0,0,0,0,0,0,0,0,0,0,0,0,0,0,0,0,0,0,0,0,0,
0,0,0,0,0,0,0,0,0,0,0,0,0,0,0,0,0,0,0,0,0,0,0,0,0,
0,0,0,0,0,0,0,0,0,0,0,0,0,0,0,0,0,0,0,0,0,0,0,0,0,
0,0,0,0,0,0,0,0,0,0,0,0,0,0,0,0,0,0,0,0,0,0,0,0,0,
0,0,0,0,0,0,0,0,0,0,0,0,0,0,0,0,0,0,0,0,0,0,0,0,0,
0,0,0,0,0,0,0,0,0,0,0,0,0,0,0,0,0,0,0,0,0,0,0,0,0,
0,0,0,0,0,0,0,0,0,0,0,0,0,0,0,0,0,0,0,0,0,0,0,0,0,
0,0,0,0,0,0,0,0,0,0,0,0,0,0,0,0,0,0,0,0,0,0,0,0,0,
0,0,0,0,0,0,0,0,0,0,0,0,0,0,0,0,0,0,0,0,0,0,0,0,0,
0,0,0,0,0,0,0,0,0,0,0,0,0,0,0,0,0,0,0,0,0,0,0,0,0,
0,0,0,0,0,0,0,0,0,0,0,0,0,0,0,0,0,0,0,0,0,0,0,0,0,
0,0,0,0,0,0,0,0,0,0,0,0,0,0,0,0,0,0,0,0,0,0,0,0,0,
0,0,0,0,0,0,0,0,0,0,0,0,0,0,0,0,0,0,0,0,0,0,0,0,0,
0,0,0,0,0,0,0,0,0,0,0,0,0,0,0,0,0,0,0,0,0,0,0,0,0,
0,0,0,0,0,0,0,0,0,0,0,0,0,0,0,0,0,0,0,0,0,0,0,0,0,
0,0,0,0,0,0,0,0,0,0,0,0,0,0,0,0,0,0,0,0,0,0,0,0,0,
0,0,0,0,0,0,0,0,0,0,0,0,0,0,0,0,0,0,0,0,0,0,0,0,0
</data>
 </layer>
 <objectgroup name="Collision">
  <object id="67" type="Pit" x="3491.58" y="1882.55" width="509.697" height="1476.12"/>
  <object id="80" type="Collision" x="3415.85" y="2306.81">
   <polygon points="242,-432 74.6667,-430.667 75.3333,-514.667 682,-512 788,-496 890,-464 990,-408 1090,-348 1292,-160 1458,-52 1598,-10 1642,-2 1704,0 1704,256 1259,62 930,-288 588,-426"/>
  </object>
  <object id="81" type="Collision" x="768.197" y="2563.61">
   <polygon points="0,0 1025.37,0 1121.5,4 1117.49,156 0,256 0,0"/>
  </object>
  <object id="142" type="Pit" x="785.091" y="3126.91" width="2725.94" height="424.97"/>
  <object id="143" type="Trampoline2" x="2692" y="2547.18" width="716" height="392.82"/>
  <object id="144" type="Trampoline1" x="1968" y="2760" width="700" height="240"/>
 </objectgroup>
 <objectgroup name="PostLoopCollision"/>
 <objectgroup name="Gems"/>
 <objectgroup name="Objects">
  <object id="33" type="Entry" x="768" y="2563.33" width="66" height="66">
   <properties>
    <property name="tags" value="flatGround"/>
   </properties>
  </object>
  <object id="34" type="Exit" x="5119.93" y="2307.76" width="66" height="66">
   <properties>
    <property name="tags" value="flatGround"/>
   </properties>
  </object>
  <object id="35" type="SpawnNextTrigger" x="1720.61" y="710" width="106.061" height="2386"/>
  <object id="79" type="Respawn" x="3780.3" y="1572.36" width="80" height="80"/>
  <object id="82" type="Gem" gid="38" x="3434.5" y="1688.5" width="43" height="43"/>
  <object id="83" type="Gem" gid="38" x="3562.5" y="1688.5" width="43" height="43"/>
  <object id="84" type="Gem" gid="38" x="3498.5" y="1496.5" width="43" height="43"/>
  <object id="86" type="Gem" gid="38" x="3434.5" y="1560.5" width="43" height="43"/>
  <object id="87" type="Gem" gid="38" x="3626.5" y="1624.5" width="43" height="43"/>
  <object id="88" type="Gem" gid="38" x="3370.5" y="1624.5" width="43" height="43"/>
  <object id="89" type="Gem" gid="38" x="3498.5" y="1752.5" width="43" height="43"/>
  <object id="90" type="Gem" gid="38" x="3562.5" y="1560.5" width="43" height="43"/>
  <object id="91" type="Gem" gid="38" x="1822.5" y="2442.5" width="43" height="43"/>
  <object id="92" type="Gem" gid="38" x="1822.5" y="2314.5" width="43" height="43"/>
  <object id="93" type="Gem" gid="38" x="1886.5" y="2378.5" width="43" height="43"/>
  <object id="94" type="Gem" gid="38" x="1758.5" y="2378.5" width="43" height="43"/>
  <object id="95" type="Gem" gid="38" x="4462.5" y="1896.5" width="43" height="43"/>
  <object id="96" type="Gem" gid="38" x="4578.5" y="1982.5" width="43" height="43"/>
  <object id="97" type="Gem" gid="38" x="4803.5" y="2182.5" width="43" height="43"/>
  <object id="98" type="Gem" gid="38" x="4930.5" y="2254.5" width="43" height="43"/>
  <object id="99" type="Gem" gid="38" x="4696.5" y="2094.5" width="43" height="43"/>
  <object id="100" type="Gem" gid="38" x="5058.5" y="2290.5" width="43" height="43"/>
  <object id="101" type="PowerStar" x="3488" y="1567" width="64" height="64"/>
 </objectgroup>
 <objectgroup name="DecorationFG">
  <object id="109" type="DecorationFG" gid="42" x="748.137" y="3199.99" width="229" height="611"/>
  <object id="110" type="DecorationFG" gid="42" x="890.995" y="3364.83" width="229" height="611"/>
  <object id="111" type="DecorationFG" gid="42" x="1055.83" y="3227.47" width="229" height="611"/>
  <object id="112" type="DecorationFG" gid="42" x="1434.95" y="3205.49" width="229" height="611"/>
  <object id="113" type="DecorationFG" gid="42" x="1583.3" y="3260.43" width="229" height="611"/>
  <object id="114" type="DecorationFG" gid="42" x="1693.19" y="3562.63" width="229" height="611"/>
  <object id="115" type="DecorationFG" gid="42" x="3418.47" y="2425.27" width="229" height="611"/>
  <object id="116" type="DecorationFG" gid="42" x="3978.91" y="2463.73" width="229" height="611"/>
  <object id="117" type="DecorationFG" gid="42" x="4627.26" y="2831.86" width="229" height="611"/>
  <object id="118" type="DecorationFG" gid="43" x="921.478" y="3102.1" width="201" height="587"/>
  <object id="119" type="DecorationFG" gid="43" x="1190.71" y="3008.7" width="201" height="587"/>
  <object id="120" type="DecorationFG" gid="43" x="1328.07" y="2871.34" width="201" height="587"/>
  <object id="121" type="DecorationFG" gid="43" x="3575.32" y="2250.46" width="201" height="587"/>
  <object id="122" type="DecorationFG" gid="43" x="3894.01" y="2349.36" width="201" height="587"/>
  <object id="123" type="DecorationFG" gid="43" x="3910.49" y="2574.63" width="201" height="587"/>
  <object id="124" type="DecorationFG" gid="43" x="4152.25" y="2173.53" width="201" height="587"/>
  <object id="125" type="DecorationFG" gid="43" x="4558.84" y="2613.09" width="201" height="587"/>
  <object id="126" type="DecorationFG" gid="43" x="4459.94" y="2668.04" width="201" height="587"/>
  <object id="127" type="DecorationFG" gid="43" x="4322.58" y="2547.16" width="201" height="587"/>
  <object id="128" type="DecorationFG" gid="42" x="4341.54" y="2826.37" width="229" height="611"/>
  <object id="130" type="DecorationFG" gid="43" x="1097.3" y="3492.21" width="201" height="587"/>
  <object id="132" type="DecorationFG" gid="43" x="1470.93" y="3530.68" width="201" height="587"/>
  <object id="133" type="DecorationFG" gid="41" x="1318.09" y="3150.17" width="177" height="359"/>
  <object id="135" type="DecorationFG" gid="41" x="3768.64" y="2194.13" width="177" height="359"/>
  <object id="136" type="DecorationFG" gid="41" x="4263.15" y="2227.09" width="177" height="359"/>
  <object id="138" type="DecorationFG" gid="41" x="4197.21" y="2408.41" width="177" height="359"/>
  <object id="139" type="DecorationFG" gid="41" x="4845.57" y="2611.71" width="177" height="359"/>
  <object id="140" type="DecorationFG" gid="41" x="4949.96" y="2562.26" width="177" height="359"/>
  <object id="141" type="DecorationFG" gid="41" x="1774.14" y="2974.35" width="177" height="359"/>
 </objectgroup>
</map>
