
{
"images": ["assets/images/ten_gametitles.png"], 
"frames": [
	[0,0,900,500],
	[0,500,900,500],
	[0,1000,210,160],
	[210,1000,210,160],
	[420,1000,210,160],
	[630,1000,210,160],
	[0,1160,210,160],
	[210,1160,210,160]
],
"animations":{
    "title_en": {"speed": 1, "frames": [0]},
    "title_es": {"speed": 1, "frames": [1]},
    "play_up_en": {"speed": 1, "frames": [2]},
    "play_over_en": {"speed": 1, "frames": [3]},
    "play_down_en": {"speed": 1, "frames": [4]},
    "play_up_es": {"speed": 1, "frames": [5]},
    "play_over_es": {"speed": 1, "frames": [6]},
    "play_down_es": {"speed": 1, "frames": [7]}
}
}
