<data>
	<additiongame>
		
		<level name="1">
			<round name="1">
				<equation>1+1</equation>
				<answer>2</answer>
			</round>
			<round name="2">
				<equation>1+2</equation>
				<answer>3</answer>
			</round>
			<round name="3">
				<equation>1+3</equation>
				<answer>4</answer>
			</round>
			<round name="4">
				<equation>2+1</equation>
				<answer>3</answer>
			</round>
			<round name="5">
				<equation>2+2</equation>
				<answer>4</answer>
			</round>
			<round name="6">
				<equation>3+1</equation>
				<answer>4</answer>
			</round>			
		</level>
		
		<level name="2">
			<round name="1">
				<equation>1+4</equation>
				<answer>5</answer>
			</round>
			<round name="2">
				<equation>4+1</equation>
				<answer>5</answer>
			</round>
			<round name="3">
				<equation>4+2</equation>
				<answer>6</answer>
			</round>
			<round name="4">
				<equation>2+4</equation>
				<answer>6</answer>
			</round>
			<round name="5">
				<equation>4+3</equation>
				<answer>7</answer>
			</round>
			<round name="6">
				<equation>3+4</equation>
				<answer>7</answer>
			</round>		
			<round name="7">
				<equation>1+5</equation>
				<answer>6</answer>
			</round>
			<round name="8">
				<equation>5+1</equation>
				<answer>6</answer>
			</round>
			<round name="9">
				<equation>5+2</equation>
				<answer>7</answer>
			</round>
			<round name="10">
				<equation>2+5</equation>
				<answer>7</answer>
			</round>
			<round name="11">
				<equation>1+6</equation>
				<answer>7</answer>
			</round>
			<round name="12">
				<equation>6+1</equation>
				<answer>7</answer>
			</round>	
			<round name="13">
				<equation>2+3</equation>
				<answer>5</answer>
			</round>
			<round name="14">
				<equation>3+2</equation>
				<answer>5</answer>
			</round>	
		</level>
		
		<level name="3">
			<round name="1">
				<equation>1+7</equation>
				<answer>8</answer>
			</round>
			<round name="2">
				<equation>7+1</equation>
				<answer>8</answer>
			</round>
			<round name="3">
				<equation>2+7</equation>
				<answer>9</answer>
			</round>
			<round name="4">
				<equation>7+2</equation>
				<answer>9</answer>
			</round>
			<round name="5">
				<equation>3+7</equation>
				<answer>10</answer>
			</round>
			<round name="6">
				<equation>7+3</equation>
				<answer>10</answer>
			</round>		
			<round name="7">
				<equation>1+8</equation>
				<answer>9</answer>
			</round>
			<round name="8">
				<equation>8+1</equation>
				<answer>9</answer>
			</round>
			<round name="9">
				<equation>2+8</equation>
				<answer>10</answer>
			</round>
			<round name="10">
				<equation>8+2</equation>
				<answer>10</answer>
			</round>
			<round name="11">
				<equation>3+5</equation>
				<answer>8</answer>
			</round>
			<round name="12">
				<equation>5+3</equation>
				<answer>8</answer>
			</round>	
			<round name="13">
				<equation>4+5</equation>
				<answer>9</answer>
			</round>
			<round name="14">
				<equation>5+4</equation>
				<answer>9</answer>
			</round>	
			<round name="15">
				<equation>5+5</equation>
				<answer>10</answer>
			</round>	
			<round name="16">
				<equation>4+4</equation>
				<answer>8</answer>
			</round>	
			<round name="17">
				<equation>2+6</equation>
				<answer>8</answer>
			</round>	
			<round name="18">
				<equation>6+2</equation>
				<answer>8</answer>
			</round>	
			<round name="19">
				<equation>3+6</equation>
				<answer>9</answer>
			</round>
			<round name="20">
				<equation>6+3</equation>
				<answer>9</answer>
			</round>
			<round name="21">
				<equation>4+6</equation>
				<answer>10</answer>
			</round>
			<round name="22">
				<equation>6+4</equation>
				<answer>10</answer>
			</round>
			<round name="23">
				<equation>1+9</equation>
				<answer>10</answer>
			</round>
			<round name="24">
				<equation>9+1</equation>
				<answer>10</answer>
			</round>
		</level>
	</additiongame>
	
	<measurementgame>
	<!-- Measurement Guide -->
	<!--
	ITEM LEGEND FOR PATTERN SEQUENCE BELOW
		1 - Life Preserver
		2 - Oar
		3 - Buoy
		4 - Log
		5 - Ducky
		6 - Toy Boat
		7 - Alligator
		8 - Fishy
	-->
		<level name="1">
			<round name="1">
				<rounddata count="2" object="2" />				
			</round>
			<round name="2">
				<rounddata count="2" object="4" />
			</round>
			<round name="3">
				<rounddata count="3" object="1" />
			</round>
			<round name="4">
				<rounddata count="3" object="4" />
			</round>
			<round name="5">
				<rounddata count="4" object="7" />
			</round>
		</level>
		
		<level name="2">
			<round name="1">
				<rounddata count="5" object="5" />				
			</round>
			<round name="2">
				<rounddata count="5" object="6" />
			</round>
			<round name="3">
				<rounddata count="6" object="8" />
			</round>
			<round name="4">
				<rounddata count="6" object="3" />
			</round>
			<round name="5">
				<rounddata count="7" object="6" />
			</round>
		</level>
		
		<level name="3">
			<round name="1">
				<rounddata count="8" object="6" />				
			</round>
			<round name="2">
				<rounddata count="8" object="3" />
			</round>
			<round name="3">
				<rounddata count="10" object="5" />
			</round>
			<round name="4">
				<rounddata count="9" object="6" />
			</round>
			<round name="5">
				<rounddata count="9" object="8" />
			</round>
		</level>
	</measurementgame>
	
	<!-- Pattern Guide -->
	<!--
	ITEM LEGEND FOR PATTERN SEQUENCE BELOW
		1 - Heart
		2 - Flower
		3 - Circle
		4 - Star
		5 - Triangle
		6 - Square
		7 - Moon
		8 - Rainbow
		9 - Butterfly
		10 - MusicNote
		11 - Diamond
		12 - Tree
	-->
	<patternsgame>
		<level name="1">
			<round name="1">
				<pattern>1,3,1,3,x,3</pattern>
				<answer name="x">1</answer>
			</round>
			<round name="2">
				<pattern>2,1,2,1,x,1</pattern>
				<answer name="x">2</answer>		
			</round>
			<round name="3">
				<pattern>3,2,3,2,3,x</pattern>
				<answer name="x">2</answer>		
			</round>			
			<round name="4">
				<pattern>4,2,4,2,4,x</pattern>
				<answer name="x">2</answer>		
			</round>
			<round name="5">
				<pattern>1,4,1,4,1,x</pattern>
				<answer name="x">4</answer>		
			</round>
			<round name="6">
				<pattern>12,8,12,8,x,8</pattern>
				<answer name="x">12</answer>	
			</round>		
			<round name="7">
				<pattern>7,5,7,5,x,5</pattern>
				<answer name="x">7</answer>	
			</round>
			<round name="8">
				<pattern>6,10,6,10,x,10</pattern>
				<answer name="x">6</answer>	
			</round>
			<round name="9">
				<pattern>9,1,9,1,x,1</pattern>
				<answer name="x">9</answer>	
			</round>		
		</level>	
		
		<level name="2">
			<round name="1">
				<pattern>1,2,3,1,2,3,1,x,y</pattern>
				<answer name="x">2</answer>
				<answer name="y">3</answer>
			</round>
			<round name="2">
				<pattern>8,10,10,8,10,10,x,y,10</pattern>
				<answer name="x">8</answer>
				<answer name="y">10</answer>	
			</round>
			<round name="3">
				<pattern>4,1,2,4,1,2,x,y,2</pattern>
				<answer name="x">4</answer>		
				<answer name="y">1</answer>		
			</round>			
			<round name="4">
				<pattern>7,5,9,7,5,9,7,x,y</pattern>
				<answer name="x">5</answer>		
				<answer name="y">9</answer>		
			</round>
			<round name="5">
				<pattern>11,11,6,11,11,6,11,x,y</pattern>
				<answer name="x">11</answer>		
				<answer name="y">6</answer>	
			</round>
			<round name="6">
				<pattern>12,8,8,12,8,8,x,y,8</pattern>
				<answer name="x">12</answer>		
				<answer name="y">8</answer>	
			</round>		
			<round name="7">
				<pattern>5,6,7,5,6,7,5,x,y</pattern>
				<answer name="x">6</answer>		
				<answer name="y">7</answer>	
			</round>
			<round name="8">
				<pattern>9,1,1,9,1,1,x,y,1</pattern>
				<answer name="x">9</answer>		
				<answer name="y">1</answer>	
			</round>
			<round name="9">
				<pattern>3,2,10,3,2,10,3,x,y</pattern>
				<answer name="x">2</answer>		
				<answer name="y">10</answer>	
			</round>	
		</level>
		
		<level name="3">
			<round name="1">
				<pattern>1,2,3,4,1,2,3,4,1,x,y,z</pattern>
				<answer name="x">2</answer>
				<answer name="y">3</answer>
				<answer name="z">4</answer>
			</round>
			<round name="2">
				<pattern>1,2,2,3,1,2,2,3,x,2,y,z</pattern>
				<answer name="x">1</answer>
				<answer name="y">2</answer>	
				<answer name="z">3</answer>	
			</round>
			<round name="3">
				<pattern>10,9,8,7,10,9,8,7,10,x,y,z</pattern>
				<answer name="x">9</answer>		
				<answer name="y">8</answer>		
				<answer name="z">7</answer>		
			</round>			
			<round name="4">
				<pattern>2,10,10,6,2,10,10,6,x,10,y,z</pattern>
				<answer name="x">2</answer>		
				<answer name="y">10</answer>		
				<answer name="z">6</answer>	
			</round>
			<round name="5">
				<pattern>3,4,11,11,3,4,11,11,x,y,11,z</pattern>
				<answer name="x">3</answer>		
				<answer name="y">4</answer>	
				<answer name="z">11</answer>	
			</round>
			<round name="6">
				<pattern>1,5,8,9,1,5,8,9,1,x,y,z</pattern>
				<answer name="x">5</answer>		
				<answer name="y">8</answer>	
				<answer name="z">9</answer>	
			</round>		
			<round name="7">
				<pattern>6,7,7,10,6,7,7,10,x,7,y,z</pattern>
				<answer name="x">6</answer>		
				<answer name="y">7</answer>	
				<answer name="z">10</answer>	
			</round>
			<round name="8">
				<pattern>3,2,4,1,3,2,4,1,x,y,z,1</pattern>
				<answer name="x">3</answer>		
				<answer name="y">2</answer>	
				<answer name="z">4</answer>	
			</round>
			<round name="9">
				<pattern>5,8,12,12,5,8,12,12,x,y,z,12</pattern>
				<answer name="x">5</answer>		
				<answer name="y">8</answer>	
				<answer name="z">12</answer>	
			</round>	
		</level>	
	</patternsgame>
	
	<sortinggame>
		<level name="1">
			<round name="1" type="color">
				<sortgroupleft answer="red" numberofobjects="3"></sortgroupleft>
				<sortgroupright answer="green" numberofobjects="3"></sortgroupright>
			</round>	
			<round name="2" type="color">
				<sortgroupleft answer="orange" numberofobjects="1"></sortgroupleft>
				<sortgroupright answer="yellow" numberofobjects="5"></sortgroupright>
			</round>	
			<round name="3" type="color">
				<sortgroupleft answer="brown" numberofobjects="3"></sortgroupleft>
				<sortgroupright answer="green" numberofobjects="3"></sortgroupright>
			</round>	
			<round name="4" type="number" >
				<sortgroupleft answer="number2" numberofobjects="4"></sortgroupleft>
				<sortgroupright answer="number3" numberofobjects="2"></sortgroupright>
			</round>	
			<round name="5" type="number">
				<sortgroupleft answer="number3" numberofobjects="4"></sortgroupleft>
				<sortgroupright answer="number4" numberofobjects="2"></sortgroupright>
			</round>	
			<round name="6" type="numberofdots" >
				<sortgroupleft answer="dots2" numberofobjects="1"></sortgroupleft>
				<sortgroupright answer="dots3" numberofobjects="5"></sortgroupright>
			</round>	
			<round name="7" type="numberofdots">
				<sortgroupleft answer="dots3" numberofobjects="3"></sortgroupleft>
				<sortgroupright answer="dots4" numberofobjects="3"></sortgroupright>
			</round>
			<round name="8" type="pattern" >
				<sortgroupleft answer="polkadots" numberofobjects="1"></sortgroupleft>
				<sortgroupright answer="stars" numberofobjects="5"></sortgroupright>
			</round>	
			<round name="9" type="pattern">
				<sortgroupleft answer="stars" numberofobjects="3"></sortgroupleft>
				<sortgroupright answer="stripes" numberofobjects="3"></sortgroupright>
			</round>			
			<round name="10" type="shape">
				<sortgroupleft answer="butterfly" numberofobjects="1"></sortgroupleft>
				<sortgroupright answer="flag" numberofobjects="5"></sortgroupright>
			</round>	
			<round name="11" type="shape">
				<sortgroupleft answer="ladybug" numberofobjects="2"></sortgroupleft>
				<sortgroupright answer="leaf" numberofobjects="4"></sortgroupright>
			</round>	
			<round name="12" type="shape">
				<sortgroupleft answer="rock" numberofobjects="3"></sortgroupleft>
				<sortgroupright answer="leaf" numberofobjects="3"></sortgroupright>
			</round>	
			<round name="13" type="size">
				<sortgroupleft answer="small" numberofobjects="2"></sortgroupleft>
				<sortgroupright answer="large" numberofobjects="4"></sortgroupright>
			</round>	
			<round name="14" type="size">
				<sortgroupleft answer="small" numberofobjects="3"></sortgroupleft>
				<sortgroupright answer="medium" numberofobjects="3"></sortgroupright>
			</round>	
		</level>
		
		<level name="2">
			<round name="1" type="color">
				<sortgroupleft answer="red" numberofobjects="6"></sortgroupleft>
				<sortgroupright answer="green" numberofobjects="2"></sortgroupright>
			</round>	
			<round name="2" type="color">
				<sortgroupleft answer="orange" numberofobjects="5"></sortgroupleft>
				<sortgroupright answer="yellow" numberofobjects="3"></sortgroupright>
			</round>	
			<round name="3" type="color">
				<sortgroupleft answer="brown" numberofobjects="1"></sortgroupleft>
				<sortgroupright answer="green" numberofobjects="7"></sortgroupright>
			</round>	
			<round name="4" type="number" >
				<sortgroupleft answer="number2" numberofobjects="5"></sortgroupleft>
				<sortgroupright answer="number3" numberofobjects="3"></sortgroupright>
			</round>	
			<round name="5" type="number">
				<sortgroupleft answer="number3" numberofobjects="4"></sortgroupleft>
				<sortgroupright answer="number4" numberofobjects="4"></sortgroupright>
			</round>	
			<round name="6" type="numberofdots" >
				<sortgroupleft answer="dots2" numberofobjects="4"></sortgroupleft>
				<sortgroupright answer="dots3" numberofobjects="4"></sortgroupright>
			</round>	
			<round name="7" type="numberofdots">
				<sortgroupleft answer="dots3" numberofobjects="5"></sortgroupleft>
				<sortgroupright answer="dots4" numberofobjects="3"></sortgroupright>
			</round>
			<round name="8" type="pattern" >
				<sortgroupleft answer="polkadots" numberofobjects="7"></sortgroupleft>
				<sortgroupright answer="stars" numberofobjects="1"></sortgroupright>
			</round>	
			<round name="9" type="pattern">
				<sortgroupleft answer="stars" numberofobjects="6"></sortgroupleft>
				<sortgroupright answer="stripes" numberofobjects="2"></sortgroupright>
			</round>			
			<round name="10" type="shape">
				<sortgroupleft answer="butterfly" numberofobjects="5"></sortgroupleft>
				<sortgroupright answer="flag" numberofobjects="3"></sortgroupright>
			</round>	
			<round name="11" type="shape">
				<sortgroupleft answer="ladybug" numberofobjects="4"></sortgroupleft>
				<sortgroupright answer="leaf" numberofobjects="4"></sortgroupright>
			</round>	
			<round name="12" type="shape">
				<sortgroupleft answer="rock" numberofobjects="5"></sortgroupleft>
				<sortgroupright answer="leaf" numberofobjects="3"></sortgroupright>
			</round>	
			<round name="13" type="size">
				<sortgroupleft answer="small" numberofobjects="6"></sortgroupleft>
				<sortgroupright answer="large" numberofobjects="2"></sortgroupright>
			</round>	
			<round name="14" type="size">
				<sortgroupleft answer="small" numberofobjects="3"></sortgroupleft>
				<sortgroupright answer="medium" numberofobjects="5"></sortgroupright>
			</round>	
		</level>
		
		<level name="3">
			<round name="1" type="color">
				<sortgroupleft answer="red" numberofobjects="6"></sortgroupleft>
				<sortgroupright answer="green" numberofobjects="6"></sortgroupright>
			</round>	
			<round name="2" type="color">
				<sortgroupleft answer="orange" numberofobjects="5"></sortgroupleft>
				<sortgroupright answer="yellow" numberofobjects="7"></sortgroupright>
			</round>	
			<round name="3" type="color">
				<sortgroupleft answer="brown" numberofobjects="4"></sortgroupleft>
				<sortgroupright answer="green" numberofobjects="8"></sortgroupright>
			</round>	
			<round name="4" type="number" >
				<sortgroupleft answer="number2" numberofobjects="3"></sortgroupleft>
				<sortgroupright answer="number3" numberofobjects="9"></sortgroupright>
			</round>	
			<round name="5" type="number">
				<sortgroupleft answer="number3" numberofobjects="2"></sortgroupleft>
				<sortgroupright answer="number4" numberofobjects="10"></sortgroupright>
			</round>	
			<round name="6" type="numberofdots" >
				<sortgroupleft answer="dots2" numberofobjects="8"></sortgroupleft>
				<sortgroupright answer="dots3" numberofobjects="4"></sortgroupright>
			</round>	
			<round name="7" type="numberofdots">
				<sortgroupleft answer="dots3" numberofobjects="7"></sortgroupleft>
				<sortgroupright answer="dots4" numberofobjects="5"></sortgroupright>
			</round>
			<round name="8" type="pattern" >
				<sortgroupleft answer="polkadots" numberofobjects="6"></sortgroupleft>
				<sortgroupright answer="stars" numberofobjects="6"></sortgroupright>
			</round>	
			<round name="9" type="pattern">
				<sortgroupleft answer="stars" numberofobjects="5"></sortgroupleft>
				<sortgroupright answer="stripes" numberofobjects="7"></sortgroupright>
			</round>			
			<round name="10" type="shape">
				<sortgroupleft answer="butterfly" numberofobjects="2"></sortgroupleft>
				<sortgroupright answer="flag" numberofobjects="10"></sortgroupright>
			</round>	
			<round name="11" type="shape">
				<sortgroupleft answer="ladybug" numberofobjects="6"></sortgroupleft>
				<sortgroupright answer="leaf" numberofobjects="6"></sortgroupright>
			</round>	
			<round name="12" type="shape">
				<sortgroupleft answer="rock" numberofobjects="4"></sortgroupleft>
				<sortgroupright answer="leaf" numberofobjects="8"></sortgroupright>
			</round>	
			<round name="13" type="size">
				<sortgroupleft answer="small" numberofobjects="7"></sortgroupleft>
				<sortgroupright answer="large" numberofobjects="5"></sortgroupright>
			</round>	
			<round name="14" type="size">
				<sortgroupleft answer="small" numberofobjects="4"></sortgroupleft>
				<sortgroupright answer="medium" numberofobjects="8"></sortgroupright>
			</round>	
		</level>
		
	</sortinggame>
</data>