<?xml version="1.0" encoding="UTF-16"?>
<TextureAtlas imagePath="scoobypie.png">
	<!-- Created with Adobe Flash CS6 version 12.0.0.481 -->
	<!-- http://www.adobe.com/products/flash.html -->
	<SubTexture name="walkloop" x="0" y="0" width="340" height="162" frameX="-8" frameY="-9" frameWidth="352" frameHeight="171"/>
	<SubTexture name="walkloop" x="0" y="0" width="340" height="162" frameX="-8" frameY="-9" frameWidth="352" frameHeight="171"/>
	<SubTexture name="walkloop" x="340" y="0" width="344" height="169" frameX="-8" frameY="0" frameWidth="352" frameHeight="171"/>
	<SubTexture name="walkloop" x="340" y="0" width="344" height="169" frameX="-8" frameY="0" frameWidth="352" frameHeight="171"/>
	<SubTexture name="walkloop" x="0" y="169" width="323" height="151" frameX="-25" frameY="-16" frameWidth="352" frameHeight="171"/>
	<SubTexture name="walkloop" x="0" y="169" width="323" height="151" frameX="-25" frameY="-16" frameWidth="352" frameHeight="171"/>
	<SubTexture name="walkloop" x="323" y="169" width="341" height="169" frameX="-7" frameY="0" frameWidth="352" frameHeight="171"/>
	<SubTexture name="walkloop" x="323" y="169" width="341" height="169" frameX="-7" frameY="0" frameWidth="352" frameHeight="171"/>
	<SubTexture name="walkloop" x="0" y="338" width="326" height="156" frameX="-22" frameY="-13" frameWidth="352" frameHeight="171"/>
	<SubTexture name="walkloop" x="0" y="338" width="326" height="156" frameX="-22" frameY="-13" frameWidth="352" frameHeight="171"/>
	<SubTexture name="walkloop" x="326" y="338" width="347" height="162" frameX="0" frameY="-4" frameWidth="352" frameHeight="171"/>
	<SubTexture name="walkloop" x="326" y="338" width="347" height="162" frameX="0" frameY="-4" frameWidth="352" frameHeight="171"/>
</TextureAtlas>
